json_logic/__init__.py
json_logic_qubit-0.9.1.dist-info/DESCRIPTION.rst
json_logic_qubit-0.9.1.dist-info/METADATA
json_logic_qubit-0.9.1.dist-info/RECORD
json_logic_qubit-0.9.1.dist-info/WHEEL
json_logic_qubit-0.9.1.dist-info/metadata.json
json_logic_qubit-0.9.1.dist-info/top_level.txt
